pylacrosseview/__init__.py
pylacrosseview/device.py
pylacrosseview/field.py
pylacrosseview/location.py
pylacrosseview/weather_station.py
pylacrosseview-0.1.5.dist-info/LICENSE
pylacrosseview-0.1.5.dist-info/WHEEL
pylacrosseview-0.1.5.dist-info/METADATA
pylacrosseview-0.1.5.dist-info/RECORD
