Metadata-Version: 2.1
Name: pylacrosseview
Version: 0.1.5
Summary: Python library that allows you to use La Crosse devices that connect with La Crosse View
License: GPLv3
Author: regulad
Author-email: regulad@outlook.com
Requires-Python: >=3.8,<4.0
Classifier: License :: Other/Proprietary License
Classifier: Programming Language :: Python :: 3
Classifier: Programming Language :: Python :: 3.8
Classifier: Programming Language :: Python :: 3.9
Requires-Dist: PyJWT[crypto] (>=2.3.0,<3.0.0)
Requires-Dist: requests (>=2.27.1,<3.0.0)
